MANIFEST.in
README.md
setup.cfg
setup.py
gu_django_multihost.egg-info/PKG-INFO
gu_django_multihost.egg-info/SOURCES.txt
gu_django_multihost.egg-info/dependency_links.txt
gu_django_multihost.egg-info/top_level.txt
gu_multihost/__init__.py
gu_multihost/admin.py
gu_multihost/metadata.py
gu_multihost/middleware.py
gu_multihost/models.py
gu_multihost/urls.py
gu_multihost/templatetags/__init__.py
gu_multihost/templatetags/multihost.py