Metadata-Version: 1.1
Name: gu-django-multihost
Version: 1.2.0
Summary: A Django application/framework which allow to serve different hostnames and urlconfs in one django application instance
Home-page: https://github.com/agushuley/django-multihost
Author: Andriy Gushuley
Author-email: agushuley@me.com
License: MIT License
Keywords: django multihost framework
Platform: any
Classifier: Development Status :: 5 - Production/Stable
Classifier: Environment :: Web Environment
Classifier: Framework :: Django
Classifier: Intended Audience :: Developers
Classifier: License :: OSI Approved :: MIT License
Classifier: Operating System :: OS Independent
Classifier: Programming Language :: Python
Classifier: Topic :: Software Development :: Libraries :: Application Frameworks
Classifier: Topic :: Software Development :: Libraries :: Python Modules
Requires: django
